tooppy/__init__.py
tooppy/taichi_cg_solver.py
tooppy/mesh/__init__.py
tooppy-2.8.3.dist-info/licenses/LICENSE
tooppy-2.8.3.dist-info/METADATA
tooppy-2.8.3.dist-info/WHEEL
tooppy-2.8.3.dist-info/top_level.txt
tooppy-2.8.3.dist-info/RECORD
