Metadata-Version: 2.4
Name: tooppy
Version: 2.8.3
Summary: A topological optimization library for python 3
Author: Shengzhi Wu
Author-email: e1124755@u.nus.edu
Classifier: Programming Language :: Python :: 3
Classifier: License :: OSI Approved :: MIT License
Classifier: Operating System :: OS Independent
Classifier: Topic :: Scientific/Engineering :: Mathematics
Classifier: Topic :: Scientific/Engineering :: Physics
License-File: LICENSE
Requires-Dist: numpy
Requires-Dist: scipy
Requires-Dist: pyvista
Requires-Dist: sympy
Requires-Dist: taichi
Dynamic: author
Dynamic: author-email
Dynamic: classifier
Dynamic: description
Dynamic: description-content-type
Dynamic: license-file
Dynamic: requires-dist
Dynamic: summary
